[
  {
    "id": 1,
    "priority": 1,
    "action": {
      "type": "block"
    },
    "condition": {
      "urlFilter": "||adbrite.com",
      "resourceTypes": [
        "sub_frame",
        "image",
        "script",
        "xmlhttprequest"
      ]
    }
  },
  {
    "id": 2,
    "priority": 1,
    "action": {
      "type": "block"
    },
    "condition": {
      "urlFilter": "||adroll.com",
      "resourceTypes": [
        "sub_frame",
        "image",
        "script",
        "xmlhttprequest"
      ]
    }
  },
  {
    "id": 3,
    "priority": 1,
    "action": {
      "type": "block"
    },
    "condition": {
      "urlFilter": "||purpleads.io",
      "resourceTypes": [
        "main_frame",
        "sub_frame",
        "image",
        "script",
        "xmlhttprequest"
      ]
    }
  }
]